dbaas_dnsapi-1.0.6.dist-info/pydist.json
dbaas_dnsapi-1.0.6.dist-info/RECORD
dbaas_dnsapi-1.0.6.dist-info/WHEEL
dbaas_dnsapi-1.0.6.dist-info/DESCRIPTION.rst
dbaas_dnsapi-1.0.6.dist-info/top_level.txt
dbaas_dnsapi-1.0.6.dist-info/METADATA
dbaas_dnsapi/models.py
dbaas_dnsapi/provider.py
dbaas_dnsapi/client.py
dbaas_dnsapi/__init__.py
dbaas_dnsapi/utils.py
dbaas_dnsapi/migrations/0002_auto__add_unique_databaseinfradnslist_name_domain.py
dbaas_dnsapi/migrations/__init__.py
dbaas_dnsapi/migrations/0001_initial.py
dbaas_dnsapi/migrations/0003_auto__add_field_planattr_dnsapi_secondary_database_domain__add_field_p.py
