Metadata-Version: 2.0
Name: dbaas-dnsapi
Version: 1.0.6
Summary: Integration between DBAAS and DNSAPI
Home-page: https://github.com/globocom/dbaas-dnsapi
Author: Ricardo Dias
Author-email: ricardo@ricardodias.org
License: BSD
Keywords: dbaas_dnsapi
Platform: UNKNOWN
Classifier: Development Status :: 2 - Pre-Alpha
Classifier: Intended Audience :: Developers
Classifier: License :: OSI Approved :: BSD License
Classifier: Natural Language :: English
Classifier: Programming Language :: Python :: 2
Classifier: Programming Language :: Python :: 2.6
Classifier: Programming Language :: Python :: 2.7
Classifier: Programming Language :: Python :: 3
Classifier: Programming Language :: Python :: 3.3
